odinson/__init__.py
odinson-0.1.0.dist-info/LICENSE
odinson-0.1.0.dist-info/METADATA
odinson-0.1.0.dist-info/WHEEL
odinson-0.1.0.dist-info/top_level.txt
odinson-0.1.0.dist-info/RECORD
